img_resizer_journal/__init__.py
img_resizer_journal/main.py
img_resizer_journal-0.0.1.dist-info/METADATA
img_resizer_journal-0.0.1.dist-info/WHEEL
img_resizer_journal-0.0.1.dist-info/top_level.txt
img_resizer_journal-0.0.1.dist-info/RECORD
