Metadata-Version: 2.1
Name: img-resizer-journal
Version: 0.0.1
Summary: python application for resizing image for publications.
Home-page: https://github.com/simonkojima/img-resizer-journal
Author: Simon Kojima
Author-email: simon.kojima@outlook.com
Project-URL: Bug Tracker, https://github.com/simonkojima/img-resizer-journal/issues
Classifier: Programming Language :: Python :: 3
Classifier: License :: OSI Approved :: MIT License
Classifier: Operating System :: OS Independent
Requires-Python: >=3.6
